{
  "$schema": "http://json-schema.org/schema",
  "id": "SchematicsStencilLibrary",
  "title": "Create a library",
  "type": "object",
  "properties": {
    "name": {
      "type": "string",
      "description": "Library name",
      "$default": {
        "$source": "argv",
        "index": 0
      },
      "x-prompt": "What name would you like to use for the library?"
    },
    "vendors": {
      "type": "object",
      "description": "vendors",
      "properties": {
        "ionic": {
          "type": "boolean",
          "x-prompt": "add vendor @ionic/core?"
        }
      }
    },
    "directory": {
      "type": "string",
      "description": "A directory where the app is placed"
    },
    "tags": {
      "type": "string",
      "description": "Add tags to the library (used for linting)"
    },
    "unitTestRunner": {
      "type": "string",
      "enum": ["karma", "jest", "none"],
      "description": "Test runner to use for unit tests",
      "default": "jest"
    }
  },
  "required": []
}
